LICENSE.md
README.md
mzfix
mzfix.cmd
mzinfo
mzinfo.cmd
setup.py
./__init__.py
./binary.py
./mzstartup.py
reasm.egg-info/PKG-INFO
reasm.egg-info/SOURCES.txt
reasm.egg-info/dependency_links.txt
reasm.egg-info/top_level.txt