Metadata-Version: 2.1
Name: reasm
Version: 0.1.0
Summary: Binary tools for various formats (e.g. MZ)
Home-page: https://github.com/excitoon/reasm
Author: Vladimir Chebotarev
Author-email: vladimir.chebotarev@gmail.com
License: MIT
Project-URL: Documentation, https://github.com/excitoon/reasm/blob/master/README.md
Project-URL: Source, https://github.com/excitoon/reasm
Project-URL: Tracker, https://github.com/excitoon/reasm/issues
Keywords: mz,executable,dos,reverse-engineering
Classifier: Development Status :: 5 - Production/Stable
Classifier: Environment :: Console
Classifier: Intended Audience :: Developers
Classifier: License :: OSI Approved :: MIT License
Classifier: Operating System :: OS Independent
Classifier: Programming Language :: Python :: 3 :: Only
Classifier: Topic :: Software Development
Classifier: Topic :: Utilities
License-File: LICENSE.md
